apckey25/APCKey25.py
apckey25/LEDBuffer.py
apckey25/__init__.py
apckey25/colors.py
apckey25/consts.py
apckey25/enums.py
apckey25-0.1.1.dist-info/LICENSE
apckey25-0.1.1.dist-info/METADATA
apckey25-0.1.1.dist-info/WHEEL
apckey25-0.1.1.dist-info/RECORD
